.DS_Store
planetterp/PlanetTerp.py
planetterp/__init__.py
planetterp/version.py
planetterp-1.0.0.dist-info/LICENSE
planetterp-1.0.0.dist-info/METADATA
planetterp-1.0.0.dist-info/WHEEL
planetterp-1.0.0.dist-info/top_level.txt
planetterp-1.0.0.dist-info/RECORD
