Metadata-Version: 2.1
Name: planetterp
Version: 1.0.0
Summary: PlanetTerp API Python wrapper
Home-page: https://github.com/planetterp/PlanetTerp-API-Python-Wrapper
Author: PlanetTerp
Author-email: admin@planetterp.com
License: UNKNOWN
Platform: UNKNOWN
Classifier: License :: OSI Approved :: MIT License
Classifier: Operating System :: OS Independent
Requires-Dist: requests
